bism/__init__.py
bism/backends/__init__.py
bism/backends/cellpose_net.py
bism/backends/cellpose_net_native.py
bism/backends/load.py
bism/backends/r_unet.py
bism/backends/unet.py
bism/backends/unetplusplus.py
bism/backends/unext.py
bism/config/__init__.py
bism/config/config.py
bism/config/valid.py
bism/eval/__init__.py
bism/eval/__main__.py
bism/eval/affinities.py
bism/eval/lsd.py
bism/loss/__init__.py
bism/loss/cl_dice.py
bism/loss/dice.py
bism/loss/jaccard.py
bism/loss/tversky.py
bism/models/__init__.py
bism/models/cellpose_net.py
bism/models/cellpose_net_native.py
bism/models/construct.py
bism/models/generic.py
bism/models/load.py
bism/models/lsd.py
bism/models/r_unet.py
bism/models/spatial_embedding.py
bism/models/unet.py
bism/models/unetplusplus.py
bism/models/unetxt.py
bism/models/unext.py
bism/modules/__init__.py
bism/modules/concat.py
bism/modules/convnext_block.py
bism/modules/drop_path.py
bism/modules/layer_norm.py
bism/modules/residual_block.py
bism/modules/runet_block.py
bism/modules/style.py
bism/modules/unet_block.py
bism/modules/upsample_layer.py
bism/targets/__init__.py
bism/targets/affinities.py
bism/targets/cellpose.py
bism/targets/local_shape_descriptors.py
bism/targets/mtlsd.py
bism/targets/omnipose.py
bism/train/__init__.py
bism/train/__main__.py
bism/train/aclsd_engine.py
bism/train/affinity_engine.py
bism/train/dataloader.py
bism/train/default_engine.py
bism/train/lsd_engine.py
bism/train/merged_transform.py
bism/train/skoots_engine.py
bism/transforms/__init__.py
bism/utils/__init__.py
bism/utils/cfg.py
bism/utils/cropping.py
bism/utils/distributed.py
bism/utils/io.py
bism/utils/morphology.py
bism/utils/visualization.py
bism/validate/__init__.py
bism/validate/benchmark.py
bism-0.0.6.dist-info/LICENSE
bism-0.0.6.dist-info/METADATA
bism-0.0.6.dist-info/WHEEL
bism-0.0.6.dist-info/entry_points.txt
bism-0.0.6.dist-info/top_level.txt
bism-0.0.6.dist-info/RECORD
