Metadata-Version: 2.1
Name: bism
Version: 0.0.6
Summary: Biomedical Image Segmentation Models (BISM)
Home-page: https://github.com/buswinka/bism
Author: Chris Buswinka
Author-email: buswinka@g.harvard.edu
Classifier: Programming Language :: Python :: 3
Requires-Python: >=3.10
License-File: LICENSE
Requires-Dist: torch (>=2.0.0)
Requires-Dist: torchvision (>=0.13.0)
Requires-Dist: bism
Requires-Dist: fastremap
Requires-Dist: zarr
Requires-Dist: tqdm
Requires-Dist: scikit-image
Requires-Dist: yacs
Requires-Dist: tensorboard
